nsipy/__init__.py
nsipy/nsi.py
nsipy-0.1.1.dist-info/LICENSE
nsipy-0.1.1.dist-info/METADATA
nsipy-0.1.1.dist-info/WHEEL
nsipy-0.1.1.dist-info/RECORD
